[
  {
    "title": "Adcreative",
    "affiliateLink": "https://free-trial.adcreative.ai/love2024",
    "description": "Placeholder description",
    "logo": "Placeholder logo URL",
    "category": "Placeholder category"
  },
  {
    "title": "Figma",
    "affiliateLink": "https://psxid.figma.com/hzcy968yp4dw-lpaypq",
    "description": "Placeholder description",
    "logo": "Placeholder logo URL",
    "category": "Placeholder category"
  },
  {
    "title": "Kissmetrics",
    "affiliateLink": "https://partnerstack.kissmetrics.io/suziedemo",
    "description": "Placeholder description",
    "logo": "Placeholder logo URL",
    "category": "Placeholder category"
  },
  {
    "title": "Murf.ai",
    "affiliateLink": "https://get.murf.ai/text-to-speech-v5n52twouv4x",
    "description": "Placeholder description",
    "logo": "Placeholder logo URL",
    "category": "Placeholder category"
  },
  {
    "title": "Eleven labs",
    "affiliateLink": "https://elevenlabs.io/?from=suziengatia5858",
    "description": "Placeholder description",
    "logo": "Placeholder logo URL",
    "category": "Placeholder category"
  },
  {
    "title": "Oyster",
    "affiliateLink": "https://oyster.partnerlinks.io/love2024",
    "description": "Placeholder description",
    "logo": "Placeholder logo URL",
    "category": "Placeholder category"
  },
  {
    "title": "Pandadoc",
    "affiliateLink": "https://pandadoc.partnerlinks.io/love2024",
    "description": "Placeholder description",
    "logo": "Placeholder logo URL",
    "category": "Placeholder category"
  },
  {
    "title": "Quillbot",
    "affiliateLink": "https://try.quillbot.com/dmv33v2kegrg",
    "description": "Placeholder description",
    "logo": "Placeholder logo URL",
    "category": "Placeholder category"
  },
  {
    "title": "Restream",
    "affiliateLink": "https://try.restream.io/love2024",
    "description": "Placeholder description",
    "logo": "Placeholder logo URL",
    "category": "Placeholder category"
  },
  {
    "title": "Social bee",
    "affiliateLink": "https://get.socialbee.io/love2024",
    "description": "Placeholder description",
    "logo": "Placeholder logo URL",
    "category": "Placeholder category"
  },
  {
    "title": "Todoist",
    "affiliateLink": "https://get.todoist.io/love2024",
    "description": "Placeholder description",
    "logo": "Placeholder logo URL",
    "category": "Placeholder category"
  },
  {
    "title": "Metricool",
    "affiliateLink": "https://i.mtr.cool/LLCHNK",
    "description": "Placeholder description",
    "logo": "Placeholder logo URL",
    "category": "Placeholder category"
  }
]